[
  {
    "number": 300,
    "question": "A server administrator needs to verify that a new 4U server will fit into the rack in the data center. Which of the following is the amount of space the 4U server requires?",
    "choices": [
      {
        "letter": "A",
        "text": "4in (10.2cm)"
      },
      {
        "letter": "B",
        "text": "5in (12.7cm)"
      },
      {
        "letter": "C",
        "text": "7in (17.8cm)"
      },
      {
        "letter": "D",
        "text": "Sin (20.3cm)"
      }
    ],
    "correct_answers": [
      "C"
    ],
    "is_multi": false
  },
  {
    "number": 301,
    "question": "A server administrator is building a pair of new storage servers. The servers will replicate; therefore, no redundancy is required, but usable capacity must be maximized. Which of the following RAID levels should the server administrator implement?",
    "choices": [
      {
        "letter": "A",
        "text": "0"
      },
      {
        "letter": "B",
        "text": "1"
      },
      {
        "letter": "C",
        "text": "5"
      },
      {
        "letter": "D",
        "text": "6"
      },
      {
        "letter": "E",
        "text": "10"
      }
    ],
    "correct_answers": [
      "A"
    ],
    "is_multi": false
  },
  {
    "number": 303,
    "question": "A user has been unable to authenticate to the company's external, web-based database after clicking a link in an email that required the user to change the account password. Which of the following steps should the company take next?",
    "choices": [
      {
        "letter": "A",
        "text": "Disable the user's account and inform the security team."
      },
      {
        "letter": "B",
        "text": "Create a new log-in to the external database."
      },
      {
        "letter": "C",
        "text": "Ask the user to use the link again to reset the password."
      },
      {
        "letter": "D",
        "text": "Reset the user's password and ask the user to log in again."
      }
    ],
    "correct_answers": [
      "A"
    ],
    "is_multi": false
  },
  {
    "number": 304,
    "question": "Which of the following types of physical security controls would most likely be a target of a social engineering attack?",
    "choices": [
      {
        "letter": "A",
        "text": "A security guard"
      },
      {
        "letter": "B",
        "text": "An access control vestibule"
      },
      {
        "letter": "C",
        "text": "Perimeter fencing"
      },
      {
        "letter": "D",
        "text": "Biometric locks"
      },
      {
        "letter": "E",
        "text": "Bollards"
      }
    ],
    "correct_answers": [
      "A"
    ],
    "is_multi": false
  },
  {
    "number": 305,
    "question": "An administrator has been asked to disable CPU hyperthreading on a server to satisfy a licensing issue. Which of the following best describes how the administrator will likely perform this action?",
    "choices": [
      {
        "letter": "A",
        "text": "Use an RDP/VNC session."
      },
      {
        "letter": "B",
        "text": "Modify the startup configuration."
      },
      {
        "letter": "C",
        "text": "Use a PowerShell/Bash script."
      },
      {
        "letter": "D",
        "text": "Use the BIOS/UEFI setup."
      }
    ],
    "correct_answers": [
      "D"
    ],
    "is_multi": false
  },
  {
    "number": 306,
    "question": "Which of the following concepts refers to prioritizing a connection that had previously worked successfully?",
    "choices": [
      {
        "letter": "A",
        "text": "Round robin"
      },
      {
        "letter": "B",
        "text": "SCP"
      },
      {
        "letter": "C",
        "text": "MRU"
      },
      {
        "letter": "D",
        "text": "Link aggregation"
      }
    ],
    "correct_answers": [
      "C"
    ],
    "is_multi": false
  },
  {
    "number": 307,
    "question": "An administrator needs to reconfigure a teamed network connection on a server in a remote data center. Which of the following will offer the most resilient connection while performing this change?",
    "choices": [
      {
        "letter": "A",
        "text": "Use of an OOB solution"
      },
      {
        "letter": "B",
        "text": "Use of a crash cart"
      },
      {
        "letter": "C",
        "text": "Use of a VNC console"
      },
      {
        "letter": "D",
        "text": "Use of an RDP console"
      }
    ],
    "correct_answers": [
      "A"
    ],
    "is_multi": false
  },
  {
    "number": 308,
    "question": "A server is only able to connect to a gigabit switch at 100Mb. Other devices are able to access the network port at full gigabit speeds, and when the server is brought to another location, it is able to connect at full gigabit speed. Which of the following should an administrator check first?",
    "choices": [
      {
        "letter": "A",
        "text": "The switch management"
      },
      {
        "letter": "B",
        "text": "The VLAN configuration"
      },
      {
        "letter": "C",
        "text": "The network cable"
      },
      {
        "letter": "D",
        "text": "The network drivers"
      }
    ],
    "correct_answers": [
      "C"
    ],
    "is_multi": false
  },
  {
    "number": 309,
    "question": "A new virtual server was deployed in a perimeter network. Users have reported the time on the server has been incorrect. The engineer has verified the configuration, and the internal time servers are configured properly. Which of the following should the engineer do to resolve this issue?",
    "choices": [
      {
        "letter": "A",
        "text": "Check the firewall rules."
      },
      {
        "letter": "B",
        "text": "Replace the CMOS battery in the server."
      },
      {
        "letter": "C",
        "text": "Restart the time servers."
      },
      {
        "letter": "D",
        "text": "Manually correct the time."
      }
    ],
    "correct_answers": [
      "A"
    ],
    "is_multi": false
  },
  {
    "number": 310,
    "question": "A systems administrator is installing Windows on an 8TB drive and would like to create a single 8TB partition on the disk. Which of the following options should the administrator use?",
    "choices": [
      {
        "letter": "A",
        "text": "VMFS"
      },
      {
        "letter": "B",
        "text": "ZFS"
      },
      {
        "letter": "C",
        "text": "GPT"
      },
      {
        "letter": "D",
        "text": "MBR"
      },
      {
        "letter": "E",
        "text": "LVM"
      }
    ],
    "correct_answers": [
      "C"
    ],
    "is_multi": false
  },
  {
    "number": 311,
    "question": "A server administrator has been asked to implement a password policy that will help mitigate the chance of a successful brute-force attack. Which of the following password policies should the administrator implement first?",
    "choices": [
      {
        "letter": "A",
        "text": "Lockout"
      },
      {
        "letter": "B",
        "text": "Length"
      },
      {
        "letter": "C",
        "text": "Complexity"
      },
      {
        "letter": "D",
        "text": "Minimum age"
      }
    ],
    "correct_answers": [
      "A"
    ],
    "is_multi": false
  },
  {
    "number": 312,
    "question": "A storage engineer responds to an alarm on a storage array and finds the battery on the RAID controller needs to be replaced. However, the replacement part will not be available for 14 days. The engineer needs to identify the impact of the failed battery on the system. Which of the following best describes the impact?",
    "choices": [
      {
        "letter": "A",
        "text": "The read and write performance will be impacted."
      },
      {
        "letter": "B",
        "text": "The read performance will be impacted."
      },
      {
        "letter": "C",
        "text": "The performance will not be impacted."
      },
      {
        "letter": "D",
        "text": "The write performance will be impacted."
      }
    ],
    "correct_answers": [
      "D"
    ],
    "is_multi": false
  },
  {
    "number": 313,
    "question": "An administrator discovers a misconfiguration that impacts all servers but can be easily corrected. The administrator has a list of affected servers and a script to correct the issue. Which of the following scripting principles should the administrator use to cycle through the list of servers to deliver the needed change?",
    "choices": [
      {
        "letter": "A",
        "text": "Linked list"
      },
      {
        "letter": "B",
        "text": "String"
      },
      {
        "letter": "C",
        "text": "Loop"
      },
      {
        "letter": "D",
        "text": "Constant"
      }
    ],
    "correct_answers": [
      "C"
    ],
    "is_multi": false
  },
  {
    "number": 314,
    "question": "A server administrator is configuring a new server in a data center in another country. Which of the following technologies should the administrator use to complete this task?",
    "choices": [
      {
        "letter": "A",
        "text": "IP KVM"
      },
      {
        "letter": "B",
        "text": "Crash cart"
      },
      {
        "letter": "C",
        "text": "Remote console"
      },
      {
        "letter": "D",
        "text": "Serial connection"
      }
    ],
    "correct_answers": [
      "A"
    ],
    "is_multi": false
  },
  {
    "number": 315,
    "question": "An administrator has deployed a new virtual server from a template. After confirming access to the subnet\u2019s gateway, the administrator is unable to log on with the domain credentials. Which of the following is the most likely cause of the issue?",
    "choices": [
      {
        "letter": "A",
        "text": "The server has not been joined to the domain."
      },
      {
        "letter": "B",
        "text": "An IP address has not been assigned to the server."
      },
      {
        "letter": "C",
        "text": "The server requires a reboot to complete the deployment process."
      },
      {
        "letter": "D",
        "text": "The domain credentials are invalid."
      }
    ],
    "correct_answers": [
      "A"
    ],
    "is_multi": false
  },
  {
    "number": 316,
    "question": "A technician recently replaced a NIC that was not functioning. Since then, no device driver is found when starting the server, and the network card is not functioning. Which of the following should the technician check first?",
    "choices": [
      {
        "letter": "A",
        "text": "The boot log"
      },
      {
        "letter": "B",
        "text": "The BIOS"
      },
      {
        "letter": "C",
        "text": "The HCL"
      },
      {
        "letter": "D",
        "text": "The event log"
      }
    ],
    "correct_answers": [
      "C"
    ],
    "is_multi": false
  },
  {
    "number": 317,
    "question": "A systems administrator is troubleshooting write speed performance issues on a server. Which of the following actions should the technician take to best resolve the issue?",
    "choices": [
      {
        "letter": "A",
        "text": "Replace the RAID controller."
      },
      {
        "letter": "B",
        "text": "Replace the RAID controller cable."
      },
      {
        "letter": "C",
        "text": "Replace the RAID cache battery."
      },
      {
        "letter": "D",
        "text": "Replace the RAID cache card."
      }
    ],
    "correct_answers": [
      "C"
    ],
    "is_multi": false
  },
  {
    "number": 318,
    "question": "A server administrator just installed a new physical server and needs to harden the applications on the server. Which of the following best describes a method of application hardening?",
    "choices": [
      {
        "letter": "A",
        "text": "Install the latest patches."
      },
      {
        "letter": "B",
        "text": "Disable unneeded hardware."
      },
      {
        "letter": "C",
        "text": "Set the boot order."
      },
      {
        "letter": "D",
        "text": "Enable a BIOS password."
      }
    ],
    "correct_answers": [
      "A"
    ],
    "is_multi": false
  },
  {
    "number": 319,
    "question": "A systems administrator recently installed a new virtual server. After completing the installation, the administrator was only able to reach a few of the servers on the network. While testing, the administrator discovered only servers that had similar IP addresses were reachable. Which of the following is the most likely cause of the issue?",
    "choices": [
      {
        "letter": "A",
        "text": "The jumbo frames are not enabled."
      },
      {
        "letter": "B",
        "text": "The subnet mask is incorrect."
      },
      {
        "letter": "C",
        "text": "There is an IP address conflict."
      },
      {
        "letter": "D",
        "text": "There is an improper DNS configuration."
      }
    ],
    "correct_answers": [
      "B"
    ],
    "is_multi": false
  },
  {
    "number": 320,
    "question": "Which of the following environmental controls must be carefully researched so the control itself does not cause the destruction of the server equipment?",
    "choices": [
      {
        "letter": "A",
        "text": "Humidity control system"
      },
      {
        "letter": "B",
        "text": "Sensors"
      },
      {
        "letter": "C",
        "text": "Fire suppression"
      },
      {
        "letter": "D",
        "text": "Heating system"
      }
    ],
    "correct_answers": [
      "C"
    ],
    "is_multi": false
  },
  {
    "number": 321,
    "question": "An application needs 10GB of RAID 1 for log files, 20GB of RAID 5 for data files, and 20GB of RAID 5 for the operating system. All disks will be 10GB in capacity. Which of the following is the minimum number of disks needed for this application?",
    "choices": [
      {
        "letter": "A",
        "text": "6"
      },
      {
        "letter": "B",
        "text": "7"
      },
      {
        "letter": "C",
        "text": "8"
      },
      {
        "letter": "D",
        "text": "9"
      }
    ],
    "correct_answers": [
      "C"
    ],
    "is_multi": false
  },
  {
    "number": 322,
    "question": "Which of the following backup methods protects all the changes that have occurred since the last full backup?",
    "choices": [
      {
        "letter": "A",
        "text": "Incremental"
      },
      {
        "letter": "B",
        "text": "Archive"
      },
      {
        "letter": "C",
        "text": "Differential"
      },
      {
        "letter": "D",
        "text": "Snapshot"
      }
    ],
    "correct_answers": [
      "C"
    ],
    "is_multi": false
  },
  {
    "number": 323,
    "question": "A legacy application server uses Telnet to allow administrators to manage it remotely. A recent security policy is denying access to any Telnet connections. Which of the following should the administrator use to manage the machine remotely via a terminal in the most secure manner?",
    "choices": [
      {
        "letter": "A",
        "text": "RDP"
      },
      {
        "letter": "B",
        "text": "Console"
      },
      {
        "letter": "C",
        "text": "SSH"
      },
      {
        "letter": "D",
        "text": "SFTP"
      }
    ],
    "correct_answers": [
      "C"
    ],
    "is_multi": false
  },
  {
    "number": 325,
    "question": "A security administrator ran a port scanning tool against a virtual server that is hosting a secure website. A list of open ports was provided as documentation. The management team has requested that non-essential ports be disabled on the firewall. Which of the following ports must remain open?",
    "choices": [
      {
        "letter": "A",
        "text": "25"
      },
      {
        "letter": "B",
        "text": "53"
      },
      {
        "letter": "C",
        "text": "443"
      },
      {
        "letter": "D",
        "text": "3389"
      },
      {
        "letter": "E",
        "text": "8080"
      }
    ],
    "correct_answers": [
      "C"
    ],
    "is_multi": false
  },
  {
    "number": 326,
    "question": "Which of the following types of locks utilizes key fobs or key cards held against a sensor/reader to gain access?",
    "choices": [
      {
        "letter": "A",
        "text": "Bolting door lock"
      },
      {
        "letter": "B",
        "text": "Combination door lock"
      },
      {
        "letter": "C",
        "text": "Electronic door lock"
      },
      {
        "letter": "D",
        "text": "Biometric door lock"
      }
    ],
    "correct_answers": [
      "C"
    ],
    "is_multi": false
  },
  {
    "number": 327,
    "question": "An administrator is configuring the storage for a new database server, which will host databases that are mainly used for archival lookups. Which of the following storage types will yield the fastest database read performance?",
    "choices": [
      {
        "letter": "A",
        "text": "NAS"
      },
      {
        "letter": "B",
        "text": "SSD"
      },
      {
        "letter": "C",
        "text": "10K rpm SATA"
      },
      {
        "letter": "D",
        "text": "15K rpm SCSI"
      }
    ],
    "correct_answers": [
      "B"
    ],
    "is_multi": false
  },
  {
    "number": 328,
    "question": "Which of the following is an architectural reinforcement that attempts to conceal the interior of an organization?",
    "choices": [
      {
        "letter": "A",
        "text": "Bollards"
      },
      {
        "letter": "B",
        "text": "Signal blocking"
      },
      {
        "letter": "C",
        "text": "Reflective glass"
      },
      {
        "letter": "D",
        "text": "Data center camouflage"
      }
    ],
    "correct_answers": [
      "C"
    ],
    "is_multi": false
  },
  {
    "number": 329,
    "question": "Which of the following often-overlooked parts of the asset life cycle can cause the greatest number of issues in relation to PII exposure?",
    "choices": [
      {
        "letter": "A",
        "text": "Usage"
      },
      {
        "letter": "B",
        "text": "End-of-life"
      },
      {
        "letter": "C",
        "text": "Procurement"
      },
      {
        "letter": "D",
        "text": "Disposal"
      }
    ],
    "correct_answers": [
      "D"
    ],
    "is_multi": false
  },
  {
    "number": 330,
    "question": "A systems engineer is configuring a new VLAN for expansion of a campus network. The engineer configures a new DHCP scope on the existing Windows DHCP server cluster and activates the scope for the clients. However, new clients in the area report they are not receiving any DHCP address information. Which of the following should the engineer do first?",
    "choices": [
      {
        "letter": "A",
        "text": "Confirm the client PCs are using the correct speed on the NIC."
      },
      {
        "letter": "B",
        "text": "Confirm the network uses the same NTP server as the clients."
      },
      {
        "letter": "C",
        "text": "Confirm the network has a helper address for the DHCP server."
      },
      {
        "letter": "D",
        "text": "Confirm the DHCP server is authorized in Active Directory."
      }
    ],
    "correct_answers": [
      "C"
    ],
    "is_multi": false
  },
  {
    "number": 331,
    "question": "Which of the following physical security concepts would most likely be used to limit personnel access to a restricted area within a data center?",
    "choices": [
      {
        "letter": "A",
        "text": "An access control vestibule"
      },
      {
        "letter": "B",
        "text": "Video surveillance"
      },
      {
        "letter": "C",
        "text": "Bollards"
      },
      {
        "letter": "D",
        "text": "Data center camouflage"
      }
    ],
    "correct_answers": [
      "A"
    ],
    "is_multi": false
  },
  {
    "number": 332,
    "question": "After installing an OS on a new server, the administrator realizes the server does not have any network connectivity. The administrator checks the network cable, and it seems to be transferring data. Which of the following should be checked next?",
    "choices": [
      {
        "letter": "A",
        "text": "NIC firmware"
      },
      {
        "letter": "B",
        "text": "IPv4 options"
      },
      {
        "letter": "C",
        "text": "DHCP options"
      },
      {
        "letter": "D",
        "text": "Firewall options"
      },
      {
        "letter": "E",
        "text": "DNS settings"
      }
    ],
    "correct_answers": [
      "B"
    ],
    "is_multi": false
  },
  {
    "number": 333,
    "question": "A technician needs to replace two RAID controllers on a database server as part of an upgrade. The server has six external storage arrays and eight internal disks that are controlled by the two RAID controllers. The technician completes the replacement and powers the systems back on, but the server OS detects several missing disks in the configuration. Which of the following steps should the technician take first to resolve this issue?",
    "choices": [
      {
        "letter": "A",
        "text": "Reboot to the RAID controller BIOS and rescan for attached disks and arrays."
      },
      {
        "letter": "B",
        "text": "Start the motherboard UEFI and confirm the RAID controller start order is correct."
      },
      {
        "letter": "C",
        "text": "Turn off the external arrays and reboot the server to redetect the internal disks first."
      },
      {
        "letter": "D",
        "text": "Turn off all components and confirm all external and internal cables before rebooting."
      }
    ],
    "correct_answers": [
      "D"
    ],
    "is_multi": false
  },
  {
    "number": 334,
    "question": "A technician is provisioning a 4TB LUN on a SAN for a Windows server. Which of the following filesystem types should be used for this server?",
    "choices": [
      {
        "letter": "A",
        "text": "ZFS"
      },
      {
        "letter": "B",
        "text": "FAT"
      },
      {
        "letter": "C",
        "text": "VMFS"
      },
      {
        "letter": "D",
        "text": "ReFS"
      }
    ],
    "correct_answers": [
      "D"
    ],
    "is_multi": false
  },
  {
    "number": 335,
    "question": "A systems administrator is setting up a second VLAN for end users. Which of the following should be provisioned for a DHCP server to be able to receive client requests from a different subnet?",
    "choices": [
      {
        "letter": "A",
        "text": "DHCP options"
      },
      {
        "letter": "B",
        "text": "NIC teaming"
      },
      {
        "letter": "C",
        "text": "Zone transfers"
      },
      {
        "letter": "D",
        "text": "Relay agent"
      },
      {
        "letter": "E",
        "text": "VLAN ID"
      }
    ],
    "correct_answers": [
      "D"
    ],
    "is_multi": false
  },
  {
    "number": 336,
    "question": "A server administrator is tasked with resolving an issue with the server\u2019s local storage. The administrator turns on the server and only two out of the four drives are found. After several reboots, an additional hard drive connects and disconnects randomly. Which of the following is most likely the cause?",
    "choices": [
      {
        "letter": "A",
        "text": "RAM"
      },
      {
        "letter": "B",
        "text": "Power supply"
      },
      {
        "letter": "C",
        "text": "Cooling failure"
      },
      {
        "letter": "D",
        "text": "CPU"
      }
    ],
    "correct_answers": [
      "B"
    ],
    "is_multi": false
  },
  {
    "number": 337,
    "question": "A virtual host has four NICs and eight VMs. Which of the following should the technician configure to enable uplink redundancy?",
    "choices": [
      {
        "letter": "A",
        "text": "VM"
      },
      {
        "letter": "B",
        "text": "vNIC"
      },
      {
        "letter": "C",
        "text": "vSwitch"
      },
      {
        "letter": "D",
        "text": "vCPU"
      },
      {
        "letter": "E",
        "text": "vHBA"
      }
    ],
    "correct_answers": [
      "C"
    ],
    "is_multi": false
  },
  {
    "number": 338,
    "question": "An engineer is configuring the RAID on a new server that will support a large database handling real-time data processing. The system needs to have the largest available space with the best write performance. Given the following disks and configurations: \u2022 Four 300GB SSD disks \u2022 Eight 1.2TB 15K SAS disks \u2022 Must include redundant OS disk Which of the following configurations would meet all the necessary requirements for the new database server?",
    "choices": [
      {
        "letter": "A",
        "text": "OS-Two SSD RAID 1 -"
      },
      {
        "letter": "B",
        "text": "OS - One SSD RAID 0 -"
      },
      {
        "letter": "C",
        "text": "OS - Two SSD RAID 1 -"
      },
      {
        "letter": "D",
        "text": "OS - Two SSD RAID 0 -"
      }
    ],
    "correct_answers": [
      "C"
    ],
    "is_multi": false
  },
  {
    "number": 339,
    "question": "An analyst is planning a new point-to-point Ethernet connection between a university campus and a newly acquired space downtown that is about 5mi (8km) away. The analyst would like the fastest possible connection speed. Which of the following would best meet the analyst\u2019s needs?",
    "choices": [
      {
        "letter": "A",
        "text": "1000BASE-LX 1Gb single-mode plenum fiber connection"
      },
      {
        "letter": "B",
        "text": "10GBASE-T 10Gb copper plenum Ethernet connection"
      },
      {
        "letter": "C",
        "text": "1000BASE-T 1Gb copper non-plenum Ethernet connection"
      },
      {
        "letter": "D",
        "text": "10GBASE-SR 10Gb multimode plenum fiber connection"
      }
    ],
    "correct_answers": [
      "A"
    ],
    "is_multi": false
  },
  {
    "number": 341,
    "question": "A virtual server that is hosting a legacy line-of-business application has been identified for a critical patch application. Which of the following should be performed prior to the patch?",
    "choices": [
      {
        "letter": "A",
        "text": "Restarting the virtual server"
      },
      {
        "letter": "B",
        "text": "Creating a snapshot"
      },
      {
        "letter": "C",
        "text": "Creating an open virtualization format"
      },
      {
        "letter": "D",
        "text": "Creating a copy of any important files"
      }
    ],
    "correct_answers": [
      "B"
    ],
    "is_multi": false
  },
  {
    "number": 342,
    "question": "Which of the following symbols is used to write a text description per line within a PowerShell script?",
    "choices": [
      {
        "letter": "A",
        "text": "%"
      },
      {
        "letter": "B",
        "text": "@"
      },
      {
        "letter": "C",
        "text": "&"
      },
      {
        "letter": "D",
        "text": "#"
      }
    ],
    "correct_answers": [
      "D"
    ],
    "is_multi": false
  },
  {
    "number": 343,
    "question": "The internal IT department policy for monitoring server health requires that evidence of server reboots be collected and reviewed on a regular basis. Which of the following should be monitored to best provide this evidence?",
    "choices": [
      {
        "letter": "A",
        "text": "Uptime"
      },
      {
        "letter": "B",
        "text": "IOPS"
      },
      {
        "letter": "C",
        "text": "CPU utilization"
      },
      {
        "letter": "D",
        "text": "Event logs"
      }
    ],
    "correct_answers": [
      "D"
    ],
    "is_multi": false
  },
  {
    "number": 344,
    "question": "A systems administrator is provisioning a SQL server with a RAID controller. The management team requires that the server be able to withstand at least a single hard drive failure, but the administrator is concerned that a computationally intensive RAID level may reduce server performance. Which of the following should the administrator choose?",
    "choices": [
      {
        "letter": "A",
        "text": "RAID 0"
      },
      {
        "letter": "B",
        "text": "RAID 5"
      },
      {
        "letter": "C",
        "text": "RAID 10"
      },
      {
        "letter": "D",
        "text": "RAID 50"
      },
      {
        "letter": "E",
        "text": "RAID 60"
      }
    ],
    "correct_answers": [
      "C"
    ],
    "is_multi": false
  },
  {
    "number": 345,
    "question": "A technician installed a new 4TB hard drive in a Windows server. Which of the following should the technician perform first to provision the new drive?",
    "choices": [
      {
        "letter": "A",
        "text": "Configure the drive as a basic disk."
      },
      {
        "letter": "B",
        "text": "Configure the drive as a dynamic disk."
      },
      {
        "letter": "C",
        "text": "Partition the drive using MBR."
      },
      {
        "letter": "D",
        "text": "Partition the drive using GPT."
      }
    ],
    "correct_answers": [
      "D"
    ],
    "is_multi": false
  },
  {
    "number": 346,
    "question": "Which of the following testing exercises for disaster recovery is primarily used to discuss incident response strategies for critical systems without affecting production data?",
    "choices": [
      {
        "letter": "A",
        "text": "Tabletop"
      },
      {
        "letter": "B",
        "text": "Backup recovery test"
      },
      {
        "letter": "C",
        "text": "Live failover"
      },
      {
        "letter": "D",
        "text": "Hot-site visit audit"
      }
    ],
    "correct_answers": [
      "A"
    ],
    "is_multi": false
  },
  {
    "number": 348,
    "question": "A company created a new DR plan. The management team would like to begin performing a review of this plan without endangering company data and with a minimal time commitment. Which of the following testing methods would best allow for this type of review?",
    "choices": [
      {
        "letter": "A",
        "text": "Simulated"
      },
      {
        "letter": "B",
        "text": "Tabletop"
      },
      {
        "letter": "C",
        "text": "Live"
      },
      {
        "letter": "D",
        "text": "Non-production"
      }
    ],
    "correct_answers": [
      "B"
    ],
    "is_multi": false
  },
  {
    "number": 349,
    "question": "Which of the following security risks provides unauthorized access to an application?",
    "choices": [
      {
        "letter": "A",
        "text": "Backdoor"
      },
      {
        "letter": "B",
        "text": "Data corruption"
      },
      {
        "letter": "C",
        "text": "Insider threat"
      },
      {
        "letter": "D",
        "text": "Social engineering"
      }
    ],
    "correct_answers": [
      "A"
    ],
    "is_multi": false
  },
  {
    "number": 350,
    "question": "Which of the following would a systems administrator most likely implement to encrypt data in transit for remote administration?",
    "choices": [
      {
        "letter": "A",
        "text": "Telnet"
      },
      {
        "letter": "B",
        "text": "SSH"
      },
      {
        "letter": "C",
        "text": "TFTP"
      },
      {
        "letter": "D",
        "text": "rlogin"
      }
    ],
    "correct_answers": [
      "B"
    ],
    "is_multi": false
  },
  {
    "number": 351,
    "question": "A Linux server requires repetitive tasks for reconfiguration. Which of the following would be the best scripting language to use?",
    "choices": [
      {
        "letter": "A",
        "text": "PowerShell"
      },
      {
        "letter": "B",
        "text": "Batch command file"
      },
      {
        "letter": "C",
        "text": "Bash"
      },
      {
        "letter": "D",
        "text": "Visual Basic"
      }
    ],
    "correct_answers": [
      "C"
    ],
    "is_multi": false
  },
  {
    "number": 352,
    "question": "Which of the following is an architectural reinforcement that is used to attempt to conceal the exterior of an organization?",
    "choices": [
      {
        "letter": "A",
        "text": "Fencing"
      },
      {
        "letter": "B",
        "text": "Bollards"
      },
      {
        "letter": "C",
        "text": "Camouflage"
      },
      {
        "letter": "D",
        "text": "Reflective glass"
      }
    ],
    "correct_answers": [
      "C"
    ],
    "is_multi": false
  },
  {
    "number": 353,
    "question": "A server administrator is installing a new server with multiple NICs on it. The Chief Information Officer has asked the administrator to ensure the new server will have the least amount of network downtime but a good amount of network speed. Which of the following best describes what the administrator should implement on the new server?",
    "choices": [
      {
        "letter": "A",
        "text": "VLAN"
      },
      {
        "letter": "B",
        "text": "vNIC"
      },
      {
        "letter": "C",
        "text": "Link aggregation"
      },
      {
        "letter": "D",
        "text": "Failover"
      }
    ],
    "correct_answers": [
      "C"
    ],
    "is_multi": false
  },
  {
    "number": 354,
    "question": "The management team has mandated the use of data-at-rest encryption for all data. Which of the following forms of encryption best achieves this goal?",
    "choices": [
      {
        "letter": "A",
        "text": "Drive"
      },
      {
        "letter": "B",
        "text": "Database"
      },
      {
        "letter": "C",
        "text": "Folder"
      },
      {
        "letter": "D",
        "text": "File"
      }
    ],
    "correct_answers": [
      "A"
    ],
    "is_multi": false
  },
  {
    "number": 355,
    "question": "A remote, embedded IoT server is having a Linux OS upgrade installed. Which of the following is the best method to stage the new media for the default boot device of the server?",
    "choices": [
      {
        "letter": "A",
        "text": "Copy and send an SSD to the site."
      },
      {
        "letter": "B",
        "text": "Copy and send a DVD to the site."
      },
      {
        "letter": "C",
        "text": "Copy and send a SATA drive to the site."
      },
      {
        "letter": "D",
        "text": "Copy and send a microSD card to the site."
      }
    ],
    "correct_answers": [
      "D"
    ],
    "is_multi": false
  },
  {
    "number": 356,
    "question": "An upper management team is investigating a security breach of the company\u2019s filesystem. It has been determined that the breach occurred within the human resources department. Which of the following was used to identify the breach in the human resources department?",
    "choices": [
      {
        "letter": "A",
        "text": "User groups"
      },
      {
        "letter": "B",
        "text": "User activity reports"
      },
      {
        "letter": "C",
        "text": "Password policy"
      },
      {
        "letter": "D",
        "text": "Multifactor authentication"
      }
    ],
    "correct_answers": [
      "B"
    ],
    "is_multi": false
  },
  {
    "number": 357,
    "question": "A new application server has been configured in the cloud to provide access to all clients within the network. On-site users are able to access all resources, but remote users are reporting issues connecting to the new application. The server administrator verifies that all users are configured with the appropriate group memberships. Which of the following is most likely causing the issue?",
    "choices": [
      {
        "letter": "A",
        "text": "Telnet connections are disabled on the server."
      },
      {
        "letter": "B",
        "text": "Role-based access control is misconfigured."
      },
      {
        "letter": "C",
        "text": "There are misconfigured firewall rules."
      },
      {
        "letter": "D",
        "text": "Group policies have not been applied."
      }
    ],
    "correct_answers": [
      "C"
    ],
    "is_multi": false
  },
  {
    "number": 358,
    "question": "A company recently implemented VoIP across a multicampus environment with ten locations. The company uses many network technologies, including fiber, copper, and wireless. Users calling between three of the locations have reported that voices sound strange. Which of the following should be monitored to narrow down the issue?",
    "choices": [
      {
        "letter": "A",
        "text": "Disk IOPS"
      },
      {
        "letter": "B",
        "text": "CPU utilization"
      },
      {
        "letter": "C",
        "text": "RAM utilization"
      },
      {
        "letter": "D",
        "text": "Network latency"
      }
    ],
    "correct_answers": [
      "D"
    ],
    "is_multi": false
  },
  {
    "number": 359,
    "question": "A server technician is installing application updates on a Linux server. When the technician tries to install a MySQL update, the GUI displays the following error message: AVC denial. Which of the following should the technician do for the MySQL update to install?",
    "choices": [
      {
        "letter": "A",
        "text": "Download the update manually and run a checksum utility to verify file integrity."
      },
      {
        "letter": "B",
        "text": "Issue the setenforce 0 command."
      },
      {
        "letter": "C",
        "text": "Create a firewall rule to allow port 3306 through the firewall."
      },
      {
        "letter": "D",
        "text": "Issue the yum -y update mysql command."
      }
    ],
    "correct_answers": [
      "B"
    ],
    "is_multi": false
  },
  {
    "number": 360,
    "question": "An administrator is troubleshooting a failed NIC in an application server. The server uses DHCP to get all IP configurations, and the server must use a specific IP address. The administrator replaces the NIC, but then the server begins to receive a different and incorrect IP address. Which of the following will enable the server to get the proper IP address?",
    "choices": [
      {
        "letter": "A",
        "text": "Modifying the MAC used on the DHCP reservation"
      },
      {
        "letter": "B",
        "text": "Updating the local hosts file with the correct IP address"
      },
      {
        "letter": "C",
        "text": "Modifying the WWNN used on the DHCP reservation"
      },
      {
        "letter": "D",
        "text": "Updating the NIC to use the correct WWNN"
      }
    ],
    "correct_answers": [
      "A"
    ],
    "is_multi": false
  },
  {
    "number": 361,
    "question": "IDS alerts indicate abnormal traffic patterns are coming from a specific server in a data center that hosts sensitive data. Upon further investigation, the server administrator notices this server has been infected with a virus due to an exploit of a known vulnerability from its database software. Which of the following should the administrator perform after removing the virus to mitigate this issue from reoccurring and to maintain high availability? (Choose three.)",
    "choices": [
      {
        "letter": "A",
        "text": "Run a vulnerability scanner on the server."
      },
      {
        "letter": "B",
        "text": "Repartition the hard drive that houses the database."
      },
      {
        "letter": "C",
        "text": "Patch the vulnerability."
      },
      {
        "letter": "D",
        "text": "Enable a host firewall."
      },
      {
        "letter": "E",
        "text": "Reformat the OS on the server."
      },
      {
        "letter": "F",
        "text": "Update the antivirus software."
      },
      {
        "letter": "G",
        "text": "Remove the database software."
      },
      {
        "letter": "H",
        "text": "Air gap the server from the network."
      }
    ],
    "correct_answers": [
      "A",
      "C",
      "F"
    ],
    "is_multi": true
  },
  {
    "number": 362,
    "question": "Which of the following types of asset management documentation is commonly used as a reference when processing the replacement of a faulty server component?",
    "choices": [
      {
        "letter": "A",
        "text": "Warranty"
      },
      {
        "letter": "B",
        "text": "Purchase order"
      },
      {
        "letter": "C",
        "text": "License"
      },
      {
        "letter": "D",
        "text": "Baseline document"
      }
    ],
    "correct_answers": [
      "A"
    ],
    "is_multi": false
  },
  {
    "number": 363,
    "question": "A systems administrator notices a newly added server cannot see any of the LUNs on the SAN. The SAN switch and the local HBA do not display any link lights. Which of the following is most likely the issue?",
    "choices": [
      {
        "letter": "A",
        "text": "A single-mode fiber cable is used in place of multimode."
      },
      {
        "letter": "B",
        "text": "The switchport is on the wrong virtual SAN."
      },
      {
        "letter": "C",
        "text": "The HBA driver needs to be installed on the server."
      },
      {
        "letter": "D",
        "text": "The zoning on the fiber switch is wrong."
      }
    ],
    "correct_answers": [
      "A"
    ],
    "is_multi": false
  },
  {
    "number": 364,
    "question": "A data center environment currently hosts more than 100 servers that include homegrown and commercial software. The management team has asked the server administrator to find a way to eliminate all company-owned data centers. Which of the following models will the administrator most likely choose to meet this need?",
    "choices": [
      {
        "letter": "A",
        "text": "SaaS"
      },
      {
        "letter": "B",
        "text": "Private"
      },
      {
        "letter": "C",
        "text": "Public"
      },
      {
        "letter": "D",
        "text": "Hybrid"
      }
    ],
    "correct_answers": [
      "C"
    ],
    "is_multi": false
  },
  {
    "number": 365,
    "question": "An administrator reviews a new server that was received from a vendor and notes the OS has been installed to a two-drive array configured with RAID 0. Which of the following best describes what will happen if a drive in that array fails?",
    "choices": [
      {
        "letter": "A",
        "text": "The server will gracefully shut down."
      },
      {
        "letter": "B",
        "text": "The server will immediately crash."
      },
      {
        "letter": "C",
        "text": "The server will operate but in read-only mode."
      },
      {
        "letter": "D",
        "text": "The server will continue to operate normally."
      }
    ],
    "correct_answers": [
      "B"
    ],
    "is_multi": false
  },
  {
    "number": 366,
    "question": "Which of the following backup types should be chosen for database servers?",
    "choices": [
      {
        "letter": "A",
        "text": "Differential"
      },
      {
        "letter": "B",
        "text": "Incremental"
      },
      {
        "letter": "C",
        "text": "Synthetic full"
      },
      {
        "letter": "D",
        "text": "Open file"
      }
    ],
    "correct_answers": [
      "C"
    ],
    "is_multi": false
  },
  {
    "number": 368,
    "question": "A server technician notices several of the servers in a data center are making loud noises. The servers are still working correctly, and no indicator lights show any issues. Which of the following should the technician do first to ensure the issues are corrected and the servers remain online?",
    "choices": [
      {
        "letter": "A",
        "text": "Replace the drives."
      },
      {
        "letter": "B",
        "text": "Upgrade the firmware."
      },
      {
        "letter": "C",
        "text": "Establish a remote connection to the server."
      },
      {
        "letter": "D",
        "text": "Replace the fans."
      }
    ],
    "correct_answers": [
      "D"
    ],
    "is_multi": false
  },
  {
    "number": 369,
    "question": "An administrator is deploying a new secure web server. The only administration method that is permitted is to connect via RDP. Which of the following ports should be allowed? (Choose two.)",
    "choices": [
      {
        "letter": "A",
        "text": "53"
      },
      {
        "letter": "B",
        "text": "80"
      },
      {
        "letter": "C",
        "text": "389"
      },
      {
        "letter": "D",
        "text": "443"
      },
      {
        "letter": "E",
        "text": "445"
      },
      {
        "letter": "F",
        "text": "3389"
      },
      {
        "letter": "G",
        "text": "8080"
      }
    ],
    "correct_answers": [
      "D",
      "F"
    ],
    "is_multi": true
  },
  {
    "number": 370,
    "question": "Which of the following attacks is the most difficult to mitigate with technology?",
    "choices": [
      {
        "letter": "A",
        "text": "Ransomware"
      },
      {
        "letter": "B",
        "text": "Backdoor"
      },
      {
        "letter": "C",
        "text": "SQL injection"
      },
      {
        "letter": "D",
        "text": "Phishing"
      }
    ],
    "correct_answers": [
      "D"
    ],
    "is_multi": false
  },
  {
    "number": 371,
    "question": "A systems administrator needs to create a data volume out of four disks with the most redundancy. Which of the following is the best solution?",
    "choices": [
      {
        "letter": "A",
        "text": "RAID 0"
      },
      {
        "letter": "B",
        "text": "RAID 1"
      },
      {
        "letter": "C",
        "text": "RAID 5"
      },
      {
        "letter": "D",
        "text": "RAID 6"
      }
    ],
    "correct_answers": [
      "B"
    ],
    "is_multi": false
  },
  {
    "number": 372,
    "question": "After a technician upgrades the firmware on a database server that is connected to two external storage arrays, the server prompts the technician to configure RAID. The technician knows the server had several configured RAID sets and thinks the firmware upgrade cleared the RAID configurations. Which of the following should the technician do to troubleshoot this issue?",
    "choices": [
      {
        "letter": "A",
        "text": "Power cycle the storage arrays and rescan RAID on the server."
      },
      {
        "letter": "B",
        "text": "Boot the OS into recovery mode and rescan the disks."
      },
      {
        "letter": "C",
        "text": "Restore the default RAID configuration and reboot."
      },
      {
        "letter": "D",
        "text": "Perform a rescan on the server's RAID controller."
      }
    ],
    "correct_answers": [
      "D"
    ],
    "is_multi": false
  },
  {
    "number": 373,
    "question": "A server administrator recently installed a kernel update to test functionality. Upon reboot, the administrator determined the new kernel was not compatible with certain server hardware and was unable to uninstall the update. Which of the following should the administrator do to mitigate further issues with the newly installed kernel version?",
    "choices": [
      {
        "letter": "A",
        "text": "Edit the bootloader configuration file and change the first kernel stanza to reflect the file location for the last known-good kernel files."
      },
      {
        "letter": "B",
        "text": "Perform a complete OS reinstall on the server using the same media that was used during the initial install."
      },
      {
        "letter": "C",
        "text": "Edit the bootloader configuration file and move the newest kernel update stanza to the end of the file."
      },
      {
        "letter": "D",
        "text": "Set a BIOS password to prevent server technicians from making any changes to the system."
      }
    ],
    "correct_answers": [
      "A"
    ],
    "is_multi": false
  },
  {
    "number": 374,
    "question": "The accounting department needs more storage and wants to retain the current data for quick read-write access. The accounting server does not have any internal drive bays available to keep both disks; however, the server does have USB 3.0 and eSATA ports available. Which of the following is the best way to accomplish the department's goals?",
    "choices": [
      {
        "letter": "A",
        "text": "Copy the existing data to an external USB 3.0 enclosure."
      },
      {
        "letter": "B",
        "text": "Place the existing data on a DVD and use the internal DVD-ROM drive."
      },
      {
        "letter": "C",
        "text": "Transfer the existing data to an external eSATA enclosure."
      },
      {
        "letter": "D",
        "text": "Move the existing data to a new, larger internal hard drive."
      }
    ],
    "correct_answers": [
      "C"
    ],
    "is_multi": false
  },
  {
    "number": 375,
    "question": "An organization is donating its outdated server equipment to a local charity. Which of the following describes what the organization should do before donating the equipment?",
    "choices": [
      {
        "letter": "A",
        "text": "Remove all the data from the server drives using the least destructive method."
      },
      {
        "letter": "B",
        "text": "Repurpose and recycle any usable server components."
      },
      {
        "letter": "C",
        "text": "Remove all the components from the server."
      },
      {
        "letter": "D",
        "text": "Review all company policies."
      }
    ],
    "correct_answers": [
      "A"
    ],
    "is_multi": false
  },
  {
    "number": 376,
    "question": "An administrator is able to ping the default gateway and internet sites by name from a file server. The file server is not able to ping the print server by name. The administrator is able to ping the file server from the print server by both IP address and computer name. When initiating an nslookup from the file server for the print server, a different IP address is returned. Which of the following is most likely the cause?",
    "choices": [
      {
        "letter": "A",
        "text": "Firewall is blocking the ICMP echo reply."
      },
      {
        "letter": "B",
        "text": "The DHCP scope option is income ct."
      },
      {
        "letter": "C",
        "text": "The DNS entries for the print server are incorrect."
      },
      {
        "letter": "D",
        "text": "The hosts file is misconfigured."
      }
    ],
    "correct_answers": [
      "C"
    ],
    "is_multi": false
  },
  {
    "number": 377,
    "question": "A site is considered a warm site when it:",
    "choices": [
      {
        "letter": "A",
        "text": "has basic technical facilities connected to it."
      },
      {
        "letter": "B",
        "text": "has faulty air conditioning that is awaiting service."
      },
      {
        "letter": "C",
        "text": "is almost ready to take over all operations from the primary site."
      },
      {
        "letter": "D",
        "text": "is fully operational and continuously providing services."
      }
    ],
    "correct_answers": [
      "A"
    ],
    "is_multi": false
  },
  {
    "number": 378,
    "question": "An administrator is working locally in a data center with multiple server racks. Which of the following is the best low-cost option to connect to any server while on site?",
    "choices": [
      {
        "letter": "A",
        "text": "Crash cart"
      },
      {
        "letter": "B",
        "text": "IP KVM"
      },
      {
        "letter": "C",
        "text": "Remote console access"
      },
      {
        "letter": "D",
        "text": "IPMI"
      }
    ],
    "correct_answers": [
      "A"
    ],
    "is_multi": false
  },
  {
    "number": 379,
    "question": "Several new components have been added to a mission-critical server, and corporate policy states all new components must meet server hardening requirements. Which of the following should be applied?",
    "choices": [
      {
        "letter": "A",
        "text": "Definition updates"
      },
      {
        "letter": "B",
        "text": "Driver updates"
      },
      {
        "letter": "C",
        "text": "OS security updates"
      },
      {
        "letter": "D",
        "text": "Application updates"
      }
    ],
    "correct_answers": [
      "B"
    ],
    "is_multi": false
  },
  {
    "number": 380,
    "question": "A server administrator is currently working on an incident. Which of the following steps should the administrator perform before resolving the issue?",
    "choices": [
      {
        "letter": "A",
        "text": "Inform the impacted users."
      },
      {
        "letter": "B",
        "text": "Make the changes to the system."
      },
      {
        "letter": "C",
        "text": "Determine the probable causes."
      },
      {
        "letter": "D",
        "text": "Identify changes to the server."
      }
    ],
    "correct_answers": [
      "C"
    ],
    "is_multi": false
  },
  {
    "number": 381,
    "question": "A server administrator deployed a new product that uses a non-standard port for web access on port 8443. However, users are unable to access the new application. The server administrator checks firewall rules and determines 8443 is allowed. Which of the following is most likely the cause of the issue?",
    "choices": [
      {
        "letter": "A",
        "text": "Intrusion detection is blocking the port."
      },
      {
        "letter": "B",
        "text": "The new application's DNS entry is incorrect."
      },
      {
        "letter": "C",
        "text": "The application should be changed to use port 443."
      },
      {
        "letter": "D",
        "text": "The core switch has a network issue."
      }
    ],
    "correct_answers": [
      "B"
    ],
    "is_multi": false
  },
  {
    "number": 382,
    "question": "Hackers recently targeted a company with an attack that resulted in a system breach, which compromised the organization's data. Because of the system breach, the administrator had to bypass normal change management procedures. Which of the following change management activities was necessary?",
    "choices": [
      {
        "letter": "A",
        "text": "Cancelled change request"
      },
      {
        "letter": "B",
        "text": "Change request postponement"
      },
      {
        "letter": "C",
        "text": "Emergency change request"
      },
      {
        "letter": "D",
        "text": "Privilege change request"
      },
      {
        "letter": "E",
        "text": "User permission change request"
      }
    ],
    "correct_answers": [
      "C"
    ],
    "is_multi": false
  },
  {
    "number": 383,
    "question": "Which of the following distributes a load across all interfaces?",
    "choices": [
      {
        "letter": "A",
        "text": "Link aggregation group"
      },
      {
        "letter": "B",
        "text": "Most recently used algorithm"
      },
      {
        "letter": "C",
        "text": "Active-passive configuration"
      },
      {
        "letter": "D",
        "text": "Failover"
      }
    ],
    "correct_answers": [
      "A"
    ],
    "is_multi": false
  },
  {
    "number": 384,
    "question": "An administrator is tasked with building an environment consisting of four servers that can each serve the same website. Which of the following concepts is described?",
    "choices": [
      {
        "letter": "A",
        "text": "Load balancing"
      },
      {
        "letter": "B",
        "text": "Direct access"
      },
      {
        "letter": "C",
        "text": "Overprovisioning"
      },
      {
        "letter": "D",
        "text": "Network teaming"
      }
    ],
    "correct_answers": [
      "A"
    ],
    "is_multi": false
  },
  {
    "number": 386,
    "question": "A server located in an IDF of a paper mill reboots every other day at random times. Which of the following should the technician perform on the server first?",
    "choices": [
      {
        "letter": "A",
        "text": "Check the power cables."
      },
      {
        "letter": "B",
        "text": "Clean the fans."
      },
      {
        "letter": "C",
        "text": "Replace the RAM."
      },
      {
        "letter": "D",
        "text": "Reattach the CPU heat sink."
      }
    ],
    "correct_answers": [
      "B"
    ],
    "is_multi": false
  },
  {
    "number": 387,
    "question": "A technician needs maximum power redundancy while configuring a new server rack. Which of the following should be specified? (Choose two.)",
    "choices": [
      {
        "letter": "A",
        "text": "Separate circuits"
      },
      {
        "letter": "B",
        "text": "Rack balancing"
      },
      {
        "letter": "C",
        "text": "Blanking panels"
      },
      {
        "letter": "D",
        "text": "High-voltage PDUs"
      },
      {
        "letter": "E",
        "text": "KVM placement"
      },
      {
        "letter": "F",
        "text": "Multiple UPSs"
      }
    ],
    "correct_answers": [
      "D",
      "F"
    ],
    "is_multi": true
  },
  {
    "number": 388,
    "question": "An administrator is installing a new server and OS. After installing the OS, the administrator logs in and wants to quickly check the network configuration. Which of the following is the best command to use to accomplish this task?",
    "choices": [
      {
        "letter": "A",
        "text": "tracert"
      },
      {
        "letter": "B",
        "text": "telnet"
      },
      {
        "letter": "C",
        "text": "ipconfig"
      },
      {
        "letter": "D",
        "text": "ping"
      }
    ],
    "correct_answers": [
      "C"
    ],
    "is_multi": false
  },
  {
    "number": 389,
    "question": "A server administrator has configured a web server. Which of the following does the administrator need to install to make the website trusted?",
    "choices": [
      {
        "letter": "A",
        "text": "IPSec"
      },
      {
        "letter": "B",
        "text": "SSL"
      },
      {
        "letter": "C",
        "text": "LDAP"
      },
      {
        "letter": "D",
        "text": "DNS"
      }
    ],
    "correct_answers": [
      "B"
    ],
    "is_multi": false
  },
  {
    "number": 390,
    "question": "A newly hired systems administrator is concerned about fileshare access at the company. The administrator turns on DLP for the fileshare and lets it propagate for a week. Which of the following can the administrator perform now?",
    "choices": [
      {
        "letter": "A",
        "text": "Manage the fileshare from an RDP session."
      },
      {
        "letter": "B",
        "text": "Audit the permissions of the fileshare."
      },
      {
        "letter": "C",
        "text": "Audit the access to the physical fileshare."
      },
      {
        "letter": "D",
        "text": "Manage the permissions from the fileshare."
      }
    ],
    "correct_answers": [
      "B"
    ],
    "is_multi": false
  },
  {
    "number": 391,
    "question": "A technician replaces a single faulted disk in the following array: RAID 10, Four 15K SAS HDD. The technician replaces it from a disk in spare parts, and the array rebuilds the data in a few minutes. After the array rebuild is complete, the system reports the IOPS on the disk array have dropped by almost 60%. Which of the following should the technician investigate first?",
    "choices": [
      {
        "letter": "A",
        "text": "Check the RAID controller for background rebuild tasks"
      },
      {
        "letter": "B",
        "text": "Check the firmware version on the newly replaced disk."
      },
      {
        "letter": "C",
        "text": "Check the RPM speed on the newly replaced disk."
      },
      {
        "letter": "D",
        "text": "Check the cache settings on the RAID controller."
      }
    ],
    "correct_answers": [
      "C"
    ],
    "is_multi": false
  },
  {
    "number": 392,
    "question": "A new company policy requires that any lost functionality must be restored within 24 hours in the event of a disaster. Which of the following describes this policy requirement?",
    "choices": [
      {
        "letter": "A",
        "text": "MTBF"
      },
      {
        "letter": "B",
        "text": "RTO"
      },
      {
        "letter": "C",
        "text": "MTTR"
      },
      {
        "letter": "D",
        "text": "RPO"
      }
    ],
    "correct_answers": [
      "B"
    ],
    "is_multi": false
  },
  {
    "number": 393,
    "question": "An administrator has been asked to copy files from a Windows server that may not conform to Windows file-naming standards. Which of the following would best facilitate the copy process?",
    "choices": [
      {
        "letter": "A",
        "text": "Robocopy"
      },
      {
        "letter": "B",
        "text": "SCP"
      },
      {
        "letter": "C",
        "text": "Drag and drop"
      },
      {
        "letter": "D",
        "text": "FTP"
      }
    ],
    "correct_answers": [
      "A"
    ],
    "is_multi": false
  },
  {
    "number": 394,
    "question": "Which of the following life-cycle management phases deals with a server that is no longer in operation?",
    "choices": [
      {
        "letter": "A",
        "text": "End-of-life"
      },
      {
        "letter": "B",
        "text": "Disposal"
      },
      {
        "letter": "C",
        "text": "Usage"
      },
      {
        "letter": "D",
        "text": "Procurement"
      }
    ],
    "correct_answers": [
      "B"
    ],
    "is_multi": false
  },
  {
    "number": 395,
    "question": "A technician is configuring a server rack that will hold ten blade servers. Which of the following safety concerns should be observed? (Choose three.)",
    "choices": [
      {
        "letter": "A",
        "text": "Floor load limitations"
      },
      {
        "letter": "B",
        "text": "Rack balancing"
      },
      {
        "letter": "C",
        "text": "Proper lifting techniques"
      },
      {
        "letter": "D",
        "text": "Power connector type"
      },
      {
        "letter": "E",
        "text": "KVM placement"
      },
      {
        "letter": "F",
        "text": "Cable management"
      },
      {
        "letter": "G",
        "text": "UPS power requirements"
      },
      {
        "letter": "H",
        "text": "PDU installation"
      },
      {
        "letter": "I",
        "text": "Separate circuits for power"
      }
    ],
    "correct_answers": [
      "A",
      "B",
      "C"
    ],
    "is_multi": true
  },
  {
    "number": 396,
    "question": "An employee who was dismissed did not return company-issued equipment. Which of the following is the most important information the IT department needs to give to the legal department?",
    "choices": [
      {
        "letter": "A",
        "text": "Labeling"
      },
      {
        "letter": "B",
        "text": "Serial number"
      },
      {
        "letter": "C",
        "text": "Warranty"
      },
      {
        "letter": "D",
        "text": "Asset tag"
      }
    ],
    "correct_answers": [
      "B"
    ],
    "is_multi": false
  },
  {
    "number": 397,
    "question": "A company needs a media server set up that provides the highest availability with a minimum requirement of at least 10TB. The company purchased five HDDs, each with a 4TB capacity. Which of the options would provide the highest fault tolerance and meet the requirements?",
    "choices": [
      {
        "letter": "A",
        "text": "RAID 0"
      },
      {
        "letter": "B",
        "text": "RAID 5"
      },
      {
        "letter": "C",
        "text": "RAID 6"
      },
      {
        "letter": "D",
        "text": "RAID 10"
      }
    ],
    "correct_answers": [
      "C"
    ],
    "is_multi": false
  },
  {
    "number": 398,
    "question": "An organization purchased six new 4TB drives for a server. An administrator is tasked with creating an efficient RAID given the minimum disk space requirement of 19TBs. Which of the following should the administrator choose to get the most efficient use of space?",
    "choices": [
      {
        "letter": "A",
        "text": "RAID 1"
      },
      {
        "letter": "B",
        "text": "RAID 5"
      },
      {
        "letter": "C",
        "text": "RAID 6"
      },
      {
        "letter": "D",
        "text": "RAID 10"
      }
    ],
    "correct_answers": [
      "B"
    ],
    "is_multi": false
  },
  {
    "number": 399,
    "question": "Which of the following backup methods can be performed while a server is running, will not interrupt files in use, and can be used to fully restore the server if needed?",
    "choices": [
      {
        "letter": "A",
        "text": "Snapshot"
      },
      {
        "letter": "B",
        "text": "Archive"
      },
      {
        "letter": "C",
        "text": "Open file"
      },
      {
        "letter": "D",
        "text": "Differential"
      }
    ],
    "correct_answers": [
      "A"
    ],
    "is_multi": false
  }
]